pylaminate/__init__.py
pylaminate/clt.py
pylaminate-0.0.5.dist-info/METADATA
pylaminate-0.0.5.dist-info/WHEEL
pylaminate-0.0.5.dist-info/top_level.txt
pylaminate-0.0.5.dist-info/RECORD
