Metadata-Version: 2.4
Name: pylaminate
Version: 0.0.5
Summary: A package for the classical laminate theory
Author-email: Ronald Grefhorst <ronald@rgde.be>
Project-URL: Homepage, https://github.com/Grefron/pylaminate
Project-URL: Issues, https://github.com/Grefron/pylaminate/issues
Classifier: Programming Language :: Python :: 3
Classifier: License :: OSI Approved :: MIT License
Classifier: Operating System :: OS Independent
Requires-Python: >=3.8
Requires-Dist: numpy
